polynomial/__init__.py
polynomial/binomial.py
polynomial/core.py
polynomial/frozen.py
polynomial/trinomial.py
py_polynomial-0.6.2.dist-info/LICENSE.txt
py_polynomial-0.6.2.dist-info/METADATA
py_polynomial-0.6.2.dist-info/WHEEL
py_polynomial-0.6.2.dist-info/top_level.txt
py_polynomial-0.6.2.dist-info/RECORD
