Metadata-Version: 2.1
Name: py-polynomial
Version: 0.6.2
Summary: Package defining mathematical single-variable polynomials.
Home-page: https://github.com/allexks/py-polynomial
Download-URL: https://github.com/allexks/py-polynomial/archive/0.6.2.tar.gz
Author: Alexander Ignatov
Author-email: yalishanda@abv.bg
License: MIT
Keywords: algebra,polynomial,polynomials,mathematics,maths,derivative,derivatives,factor,factors,root,roots,terms,coefficients,quadratic,linear,sympy,numpy
Classifier: Development Status :: 3 - Alpha
Classifier: Intended Audience :: Developers
Classifier: Topic :: Software Development :: Build Tools
Classifier: License :: OSI Approved :: MIT License
Classifier: Programming Language :: Python :: 3
Classifier: Programming Language :: Python :: 3.6
Classifier: Programming Language :: Python :: 3.7
Classifier: Programming Language :: Python :: 3.8
License-File: LICENSE.txt
